design.v
module dual_address_ram(
	input clk,
	input wr_en,
	input [7:0] data_in,
	input [3:0] addr_in_0,
	input [3:0] addr_in_1,
	input port_en_0,
	input port_en_1,
	output [7:0] data_out_0,
	output [7:0] data_out_1);

	reg [7:0] ram [0:15];

	always @(posedge clk) begin
		if (port_en_0 == 1 && wr_en == 1) 
			ram[addr_in_0] <= data_in;
		if (port_en_1 == 1 && wr_en == 1)
			ram[addr_in_1] <= data_in;
		if ((port_en_0 && port_en_1) && (addr_in_0 == addr_in_1))
			ram[addr_in_0] <= xx;
	end

	assign data_out_0 = port_en_0 ? ram[addr_in_0] : 'dZ;
	assign data_out_1 = port_en_1 ? ram[addr_in_1] : 'dZ;

endmodule

testbench.v
module dual_address_ram_tb();

	// Inputs
	reg clk;
	reg wr_en;
	reg [7:0] data_in;
	reg [3:0] addr_in_0;
	reg [3:0] addr_in_1;
	reg port_en_0;
	reg port_en_1;

	// Outputs
	wire [7:0] data_out_0;
	wire [7:0] data_out_1;
	
	integer i;

	// Instantiate the Unit Under Test (UUT)
	dual_address_ram uut (
		.clk(clk), 
		.wr_en(wr_en), 
		.data_in(data_in), 
		.addr_in_0(addr_in_0), 
		.addr_in_1(addr_in_1), 
		.port_en_0(port_en_0), 
		.port_en_1(port_en_1), 
		.data_out_0(data_out_0), 
		.data_out_1(data_out_1)
	);
	
	always begin
	  #5;
	  clk = ~clk;
	end

	initial begin
		// Initialize Inputs
		clk = 1;
		data_in = 0;
		addr_in_0 = 0;
		addr_in_1 = 0;
		wr_en = 1;
		port_en_0 = 1;
		port_en_1 = 1;
		#20;

		for (integer i = 1; i <= 16; i = i + 1) begin
			data_in = i;
			addr_in_0 = i - 1;
			#10;
		end

		for (integer i = 1; i <= 16; i = i + 1) begin
			data_in = 16 - i;
			addr_in_1 = i - 1;
			#10;
		end
			
		// Add stimulus here
		#30;
		port_en_0 = 0;
		port_en_1 = 0;

		for (integer i = 0; i <= 16; i = i + 1) begin
		  addr_in_0 = i;
		  addr_in_1 = i;
		  #20;
		end

		#30;
		$finish;
	end

	initial begin
	  $dumpfile("dump.vcd");
	  $dumpvars(0);
	end
	
endmodule

dump.vcd
$date
	Fri Feb 07 17:49:35 2025
$end
$version
	Icarus Verilog
$end
$timescale
	1s
$end
$scope module dual_address_ram_tb $end
$var wire 8 ! data_out_1 [7:0] $end
$var wire 8 " data_out_0 [7:0] $end
$var reg 4 # addr_in_0 [3:0] $end
$var reg 4 $ addr_in_1 [3:0] $end
$var reg 1 % clk $end
$var reg 8 & data_in [7:0] $end
$var reg 1 ' port_en_0 $end
$var reg 1 ( port_en_1 $end
$var reg 1 ) wr_en $end
$scope module uut $end
$var wire 4 * addr_in_0 [3:0] $end
$var wire 4 + addr_in_1 [3:0] $end
$var wire 1 % clk $end
$var wire 8 , data_in [7:0] $end
$var wire 1 ' port_en_0 $end
$var wire 1 ( port_en_1 $end
$var wire 1 ) wr_en $end
$var wire 8 - data_out_1 [7:0] $end
$var wire 8 . data_out_0 [7:0] $end
$upscope $end
$scope begin $ivl_for_loop0 $end
$var integer 32 / i [31:0] $end
$upscope $end
$scope begin $ivl_for_loop1 $end
$var integer 32 0 i [31:0] $end
$upscope $end
$scope begin $ivl_for_loop2 $end
$var integer 32 1 i [31:0] $end
$upscope $end
$upscope $end
$enddefinitions $end
$comment Show the parameter values. $end
$dumpall
$end
#0
$dumpvars
bx 1
bx 0
bx /
b0 .
b0 -
b0 ,
b0 +
b0 *
1)
1(
1'
b0 &
1%
b0 $
b0 #
b0 "
b0 !
$end
#5
0%
#10
1%
#15
0%
#20
b1 "
b1 .
b1 !
b1 -
1%
b1 &
b1 ,
b1 /
#25
0%
#30
b10 !
b10 -
b10 "
b10 .
1%
b1 #
b1 *
b10 &
b10 ,
b10 /
#35
0%
#40
b11 !
b11 -
b11 "
b11 .
1%
b10 #
b10 *
b11 &
b11 ,
b11 /
#45
0%
#50
b100 !
b100 -
b100 "
b100 .
1%
b11 #
b11 *
b100 &
b100 ,
b100 /
#55
0%
#60
b101 !
b101 -
b101 "
b101 .
1%
b100 #
b100 *
b101 &
b101 ,
b101 /
#65
0%
#70
b110 !
b110 -
b110 "
b110 .
1%
b101 #
b101 *
b110 &
b110 ,
b110 /
#75
0%
#80
b111 !
b111 -
b111 "
b111 .
1%
b110 #
b110 *
b111 &
b111 ,
b111 /
#85
0%
#90
b1000 !
b1000 -
b1000 "
b1000 .
1%
b111 #
b111 *
b1000 &
b1000 ,
b1000 /
#95
0%
#100
b1001 !
b1001 -
b1001 "
b1001 .
1%
b1000 #
b1000 *
b1001 &
b1001 ,
b1001 /
#105
0%
#110
b1010 !
b1010 -
b1010 "
b1010 .
1%
b1001 #
b1001 *
b1010 &
b1010 ,
b1010 /
#115
0%
#120
b1011 !
b1011 -
b1011 "
b1011 .
1%
b1010 #
b1010 *
b1011 &
b1011 ,
b1011 /
#125
0%
#130
b1100 !
b1100 -
b1100 "
b1100 .
1%
b1011 #
b1011 *
b1100 &
b1100 ,
b1100 /
#135
0%
#140
b1101 !
b1101 -
b1101 "
b1101 .
1%
b1100 #
b1100 *
b1101 &
b1101 ,
b1101 /
#145
0%
#150
b1110 !
b1110 -
b1110 "
b1110 .
1%
b1101 #
b1101 *
b1110 &
b1110 ,
b1110 /
#155
0%
#160
b1111 !
b1111 -
b1111 "
b1111 .
1%
b1110 #
b1110 *
b1111 &
b1111 ,
b1111 /
#165
0%
#170
b10000 !
b10000 -
b10000 "
b10000 .
1%
b1111 #
b1111 *
b10000 &
b10000 ,
b10000 /
#175
0%
#180
b1111 !
b1111 -
b1111 "
b1111 .
1%
b1111 &
b1111 ,
b1 0
b10001 /
#185
0%
#190
b1110 "
b1110 .
b1110 !
b1110 -
1%
b1 $
b1 +
b1110 &
b1110 ,
b10 0
#195
0%
#200
b1101 "
b1101 .
b1101 !
b1101 -
1%
b10 $
b10 +
b1101 &
b1101 ,
b11 0
#205
0%
#210
b1100 "
b1100 .
b1100 !
b1100 -
1%
b11 $
b11 +
b1100 &
b1100 ,
b100 0
#215
0%
#220
b1011 "
b1011 .
b1011 !
b1011 -
1%
b100 $
b100 +
b1011 &
b1011 ,
b101 0
#225
0%
#230
b1010 "
b1010 .
b1010 !
b1010 -
1%
b101 $
b101 +
b1010 &
b1010 ,
b110 0
#235
0%
#240
b1001 "
b1001 .
b1001 !
b1001 -
1%
b110 $
b110 +
b1001 &
b1001 ,
b111 0
#245
0%
#250
b1000 "
b1000 .
b1000 !
b1000 -
1%
b111 $
b111 +
b1000 &
b1000 ,
b1000 0
#255
0%
#260
b111 "
b111 .
b111 !
b111 -
1%
b1000 $
b1000 +
b111 &
b111 ,
b1001 0
#265
0%
#270
b110 "
b110 .
b110 !
b110 -
1%
b1001 $
b1001 +
b110 &
b110 ,
b1010 0
#275
0%
#280
b101 "
b101 .
b101 !
b101 -
1%
b1010 $
b1010 +
b101 &
b101 ,
b1011 0
#285
0%
#290
b100 "
b100 .
b100 !
b100 -
1%
b1011 $
b1011 +
b100 &
b100 ,
b1100 0
#295
0%
#300
b11 "
b11 .
b11 !
b11 -
1%
b1100 $
b1100 +
b11 &
b11 ,
b1101 0
#305
0%
#310
b10 "
b10 .
b10 !
b10 -
1%
b1101 $
b1101 +
b10 &
b10 ,
b1110 0
#315
0%
#320
b1 "
b1 .
b1 !
b1 -
1%
b1110 $
b1110 +
b1 &
b1 ,
b1111 0
#325
0%
#330
b0 "
b0 .
b0 !
b0 -
1%
b1111 $
b1111 +
b0 &
b0 ,
b10000 0
#335
0%
#340
1%
b10001 0
#345
0%
#350
1%
#355
0%
#360
1%
#365
0%
#370
bz !
bz -
bz "
bz .
1%
b0 $
b0 +
b0 #
b0 *
b0 1
0(
0'
#375
0%
#380
1%
#385
0%
#390
1%
b1 $
b1 +
b1 #
b1 *
b1 1
#395
0%
#400
1%
#405
0%
#410
1%
b10 $
b10 +
b10 #
b10 *
b10 1
#415
0%
#420
1%
#425
0%
#430
1%
b11 $
b11 +
b11 #
b11 *
b11 1
#435
0%
#440
1%
#445
0%
#450
1%
b100 $
b100 +
b100 #
b100 *
b100 1
#455
0%
#460
1%
#465
0%
#470
1%
b101 $
b101 +
b101 #
b101 *
b101 1
#475
0%
#480
1%
#485
0%
#490
1%
b110 $
b110 +
b110 #
b110 *
b110 1
#495
0%
#500
1%
#505
0%
#510
1%
b111 $
b111 +
b111 #
b111 *
b111 1
#515
0%
#520
1%
#525
0%
#530
1%
b1000 $
b1000 +
b1000 #
b1000 *
b1000 1
#535
0%
#540
1%
#545
0%
#550
1%
b1001 $
b1001 +
b1001 #
b1001 *
b1001 1
#555
0%
#560
1%
#565
0%
#570
1%
b1010 $
b1010 +
b1010 #
b1010 *
b1010 1
#575
0%
#580
1%
#585
0%
#590
1%
b1011 $
b1011 +
b1011 #
b1011 *
b1011 1
#595
0%
#600
1%
#605
0%
#610
1%
b1100 $
b1100 +
b1100 #
b1100 *
b1100 1
#615
0%
#620
1%
#625
0%
#630
1%
b1101 $
b1101 +
b1101 #
b1101 *
b1101 1
#635
0%
#640
1%
#645
0%
#650
1%
b1110 $
b1110 +
b1110 #
b1110 *
b1110 1
#655
0%
#660
1%
#665
0%
#670
1%
b1111 $
b1111 +
b1111 #
b1111 *
b1111 1
#675
0%
#680
1%
#685
0%
#690
1%
b0 $
b0 +
b0 #
b0 *
b10000 1
#695
0%
#700
1%
#705
0%
#710
1%
b10001 1
